setup.cfg
setup.py
refreshbooks/__init__.py
refreshbooks/adapters.py
refreshbooks/api.py
refreshbooks/client.py
refreshbooks/elements.py
refreshbooks/exceptions.py
refreshbooks/transport.py
refreshbooks.egg-info/PKG-INFO
refreshbooks.egg-info/SOURCES.txt
refreshbooks.egg-info/dependency_links.txt
refreshbooks.egg-info/requires.txt
refreshbooks.egg-info/top_level.txt
refreshbooks/optional/__init__.py
refreshbooks/optional/oauth.py
refreshbooks/transports/__init__.py
refreshbooks/transports/use_httplib2.py
refreshbooks/transports/use_requests.py
refreshbooks/transports/use_urllib2.py