Metadata-Version: 1.1
Name: refreshbooks
Version: 2.0
Summary: A client library for the FreshBooks API
Home-page: http://github.com/freshbooks/refreshbooks
Author: Owen Jacobson
Author-email: api@freshbooks.com
License: UNKNOWN
Download-URL: http://pypi.python.org/pypi/refreshbooks/
Platform: UNKNOWN
Classifier: Development Status :: 4 - Beta
Classifier: Intended Audience :: Developers
Classifier: License :: OSI Approved :: MIT License
Classifier: Operating System :: OS Independent
Classifier: Topic :: Software Development :: Libraries :: Python Modules
